<?xml version="1.0" encoding="utf-8"?>
<AdditionalInfo>
  <CTypeInfo>
      <RtlPort>
        <name>leds_port</name>
        <type>Signed</type>
        <fractionWidth>0</fractionWidth>
      </RtlPort>
      <RtlPort>
        <name>leds_port_ap_vld</name>
        <type>bool</type>
        <fractionWidth>0</fractionWidth>
      </RtlPort>
      <RtlPort>
        <name>W1_out_address0</name>
        <type>Unsigned</type>
        <fractionWidth>0</fractionWidth>
      </RtlPort>
      <RtlPort>
        <name>W1_out_address1</name>
        <type>Unsigned</type>
        <fractionWidth>0</fractionWidth>
      </RtlPort>
      <RtlPort>
        <name>W1_out_ce0</name>
        <type>bool</type>
        <fractionWidth>0</fractionWidth>
      </RtlPort>
      <RtlPort>
        <name>W1_out_ce1</name>
        <type>bool</type>
        <fractionWidth>0</fractionWidth>
      </RtlPort>
      <RtlPort>
        <name>W1_out_d0</name>
        <type>Signed</type>
        <fractionWidth>0</fractionWidth>
      </RtlPort>
      <RtlPort>
        <name>W1_out_d1</name>
        <type>Signed</type>
        <fractionWidth>0</fractionWidth>
      </RtlPort>
      <RtlPort>
        <name>W1_out_we0</name>
        <type>bool</type>
        <fractionWidth>0</fractionWidth>
      </RtlPort>
      <RtlPort>
        <name>W1_out_we1</name>
        <type>bool</type>
        <fractionWidth>0</fractionWidth>
      </RtlPort>
      <RtlPort>
        <name>W2_out_address0</name>
        <type>Unsigned</type>
        <fractionWidth>0</fractionWidth>
      </RtlPort>
      <RtlPort>
        <name>W2_out_ce0</name>
        <type>bool</type>
        <fractionWidth>0</fractionWidth>
      </RtlPort>
      <RtlPort>
        <name>W2_out_d0</name>
        <type>Signed</type>
        <fractionWidth>0</fractionWidth>
      </RtlPort>
      <RtlPort>
        <name>W2_out_we0</name>
        <type>bool</type>
        <fractionWidth>0</fractionWidth>
      </RtlPort>
  </CTypeInfo>
  <DesignConstraint>
    <clk_period>10</clk_period>
  </DesignConstraint>
  <Machine>64</Machine>
  <modelParameters>
    <combinational>0</combinational>
    <latency>29</latency>
    <II>30</II>
  </modelParameters>
</AdditionalInfo>
